{
  "parent": "neofunction:.clock/1s",
  "criteria": {
    "requirement": {
      "trigger": "minecraft:location",
      "conditions": {
        "player": [
          {
            "condition": "minecraft:entity_scores",
            "entity": "this",
            "scores": {
              "health": {
                "min": 1
              }
            }
          },
          {
            "condition": "minecraft:entity_properties",
            "entity": "this",
            "predicate": {
              "location": {
                "position": {
                  "y": {
                    "min": 384
                  }
                }
              }
            }
          }
        ]
      }
    }
  },
  "rewards": {
    "function": "neofunction:system/adv/location/heaven"
  }
}
